cv2/LICENSE-3RD-PARTY.txt
cv2/LICENSE.txt
cv2/__init__.py
cv2/cv2.cp38-win32.pyd
cv2/opencv_videoio_ffmpeg451.dll
cv2/version.py
cv2/data/__init__.py
cv2/data/haarcascade_eye.xml
cv2/data/haarcascade_eye_tree_eyeglasses.xml
cv2/data/haarcascade_frontalcatface.xml
cv2/data/haarcascade_frontalcatface_extended.xml
cv2/data/haarcascade_frontalface_alt.xml
cv2/data/haarcascade_frontalface_alt2.xml
cv2/data/haarcascade_frontalface_alt_tree.xml
cv2/data/haarcascade_frontalface_default.xml
cv2/data/haarcascade_fullbody.xml
cv2/data/haarcascade_lefteye_2splits.xml
cv2/data/haarcascade_licence_plate_rus_16stages.xml
cv2/data/haarcascade_lowerbody.xml
cv2/data/haarcascade_profileface.xml
cv2/data/haarcascade_righteye_2splits.xml
cv2/data/haarcascade_russian_plate_number.xml
cv2/data/haarcascade_smile.xml
cv2/data/haarcascade_upperbody.xml
opencovis_python_headless-4.5.1.84.dist-info/LICENSE-3RD-PARTY.txt
opencovis_python_headless-4.5.1.84.dist-info/LICENSE.txt
opencovis_python_headless-4.5.1.84.dist-info/METADATA
opencovis_python_headless-4.5.1.84.dist-info/WHEEL
opencovis_python_headless-4.5.1.84.dist-info/top_level.txt
opencovis_python_headless-4.5.1.84.dist-info/RECORD
